apiruns_swagger/__init__.py
apiruns_swagger/swagger/__init__.py
apiruns_swagger/swagger/adapters.py
apiruns_swagger/transpirables.py
apiruns_swagger-0.0.6.dist-info/LICENSE
apiruns_swagger-0.0.6.dist-info/WHEEL
apiruns_swagger-0.0.6.dist-info/METADATA
apiruns_swagger-0.0.6.dist-info/RECORD
